crackle_api_helpers/__init__.py
crackle_api_helpers/api_monitoring_tests.py
crackle_api_helpers/api_wrapper.py
crackle_api_helpers/auth_key_missing_error.py
crackle_api_helpers/session.py
crackle_api_helpers/tests.py
crackle_api_helpers/authentication/__init__.py
crackle_api_helpers/authentication/authentication.py
crackle_api_helpers/authentication/authentication_helpers.py
crackle_api_helpers/monitoring/__init__.py
crackle_api_helpers/monitoring/monitoring_wrapper.py
crackle_api_helpers/monitoring/platform_config.yaml
extensions/__init__.py
extensions/yaml_parser.py
nms_api_helpers-0.5.dist-info/METADATA
nms_api_helpers-0.5.dist-info/RECORD
nms_api_helpers-0.5.dist-info/WHEEL
nms_api_helpers-0.5.dist-info/top_level.txt
nms_api_helpers-0.5.dist-info/zip-safe
phoenix_api_helpers/__init__.py
phoenix_api_helpers/api_wrapper.py
phoenix_api_helpers/environment_config.yaml
phoenix_api_helpers/session.py
phoenix_api_helpers/tests.py
