Metadata-Version: 2.1
Name: nms-api-helpers
Version: 0.5
Summary: nms api helpers
Home-page: https://github.com/Jandon-Ltd/nms-api-helpers
Author: Jandon Limited
Author-email: automation@jandon.co.uk
License: MIT
Platform: UNKNOWN
Requires-Dist: pyyaml
Requires-Dist: requests
Requires-Dist: urllib3
